transit_chem/__init__.py
transit_chem/__main__.py
transit_chem/atom.py
transit_chem/basis.py
transit_chem/cli.py
transit_chem/config.py
transit_chem/constants.py
transit_chem/elements.py
transit_chem/hopping_matrix.py
transit_chem/molecule.py
transit_chem/operators.py
transit_chem/plotting.py
transit_chem/potentials.py
transit_chem/time_evolution.py
transit_chem/utils.py
transit_chem/validation.py
transit_chem-0.6.2.dist-info/entry_points.txt
transit_chem-0.6.2.dist-info/LICENSE
transit_chem-0.6.2.dist-info/WHEEL
transit_chem-0.6.2.dist-info/METADATA
transit_chem-0.6.2.dist-info/RECORD
