Metadata-Version: 2.1
Name: transit-chem
Version: 0.6.2
Summary: Quantifying Probabilistic Electron Transit times.
License: MIT
Author: Evan Curtin
Author-email: fakeemail@gmail.com
Requires-Python: >=3.7.0,<4.0.0
Classifier: License :: OSI Approved :: MIT License
Classifier: Programming Language :: Python :: 3
Classifier: Programming Language :: Python :: 3.7
Classifier: Programming Language :: Python :: 3.8
Requires-Dist: attrs (>=19.3,<20.0)
Requires-Dist: cattrs (>=1.0,<2.0)
Requires-Dist: click (>=7.0,<8.0)
Requires-Dist: joblib (>=0.14.1,<0.15.0)
Requires-Dist: loguru (>=0.4.0,<0.5.0)
Requires-Dist: matplotlib (>=3.1,<4.0)
Requires-Dist: numba (>=0.43.0,<0.44.0)
Requires-Dist: numpy (>=1.17,<2.0)
Requires-Dist: scipy (>=1.3,<2.0)
Requires-Dist: tqdm (>=4.39,<5.0)
